New_template/FW_with_core_switch.py
New_template/Library.py
New_template/__init__.py
FP_SMC_ALS-0.0.1.dist-info/LICENSE
FP_SMC_ALS-0.0.1.dist-info/METADATA
FP_SMC_ALS-0.0.1.dist-info/WHEEL
FP_SMC_ALS-0.0.1.dist-info/top_level.txt
FP_SMC_ALS-0.0.1.dist-info/RECORD
