Metadata-Version: 2.1
Name: FP-SMC-ALS
Version: 0.0.1
Summary: Forcepoint SMC
Author: NeuralNine (Florian Dedov)
Author-email: <mail@neuralnine.com>
Keywords: SMC,FP,Forcepoint,NGFW
Classifier: Development Status :: 1 - Planning
Classifier: Intended Audience :: Developers
Classifier: Programming Language :: Python :: 3
Classifier: Operating System :: Unix
Classifier: Operating System :: MacOS :: MacOS X
Classifier: Operating System :: Microsoft :: Windows
License-File: LICENSE
